{"ProjectBreakpoints":"{\"Value\":{},\"CodeBreakpoints\":{}}","ProjectSettings":"{\"IncludeSourcesByDefault\":true,\"RemoveUnusedDependencies\":false}","OpenedDocuments":"[{\"DocumentPath\":\"TestCase.xaml\",\"FactoryId\":\"{ACB8E7BA-F093-44C1-9B50-33ECA51AAE18}\"}]","ProjectActivitiesViewState":"{\"TestCase.xaml\":[{\"ActivityIdRef\":\"LogMessage_1\",\"IsAdvancedOptionsExpanded\":false,\"Widgets\":{}},{\"ActivityIdRef\":\"RunTests_1\",\"IsAdvancedOptionsExpanded\":false,\"Categories\":{\"Common\":true,\"Input\":true,\"Output\":true},\"Widgets\":{}}],\"CoverageMergeHelperWorkflow.xaml\":[{\"ActivityIdRef\":\"CoverageMergeActivity_1\",\"IsAdvancedOptionsExpanded\":false,\"Widgets\":{}}]}","Compiler":"2","ProjectWatches":"{\"Value\":[]}"}